MANIFEST.in
README.md
setup.cfg
setup.py
elasticmock_additional_apis/__init__.py
elasticmock_additional_apis/fake_cluster.py
elasticmock_additional_apis/fake_elasticsearch.py
elasticmock_additional_apis/fake_indices.py
elasticmock_additional_apis.egg-info/PKG-INFO
elasticmock_additional_apis.egg-info/SOURCES.txt
elasticmock_additional_apis.egg-info/dependency_links.txt
elasticmock_additional_apis.egg-info/requires.txt
elasticmock_additional_apis.egg-info/top_level.txt
elasticmock_additional_apis/behaviour/__init__.py
elasticmock_additional_apis/behaviour/server_failure.py
elasticmock_additional_apis/elasticmock/__init__.py
elasticmock_additional_apis/elasticmock/fake_cluster.py
elasticmock_additional_apis/elasticmock/fake_elasticsearch.py
elasticmock_additional_apis/elasticmock/fake_indices.py
elasticmock_additional_apis/elasticmock/behaviour/__init__.py
elasticmock_additional_apis/elasticmock/behaviour/server_failure.py
elasticmock_additional_apis/elasticmock/utilities/__init__.py
elasticmock_additional_apis/elasticmock/utilities/decorator.py
elasticmock_additional_apis/utilities/__init__.py
elasticmock_additional_apis/utilities/decorator.py