Metadata-Version: 1.1
Name: elasticmock-additional-apis
Version: 0.9
Summary: Extended elasticmock module with additional Elasticsearch index APIs
Home-page: https://github.com/Tessg22/elasticmock_additional_apis
Author: Tereza Gabrielova
Author-email: terezagabrielova@yahoo.com
License: MIT
Download-URL: https://github.com/Tessg22/elasticmock_additional_apis/archive/v_01.tar.gz
Keywords: Tagsunittest,mock,elasticsearch
Platform: UNKNOWN
Classifier: Development Status :: 4 - Beta
Classifier: Intended Audience :: Developers
Classifier: Topic :: Software Development :: Build Tools
Classifier: License :: OSI Approved :: MIT License
Classifier: Programming Language :: Python :: 3
